[  
   {  
      "id":"272",
      "member_id":"81",
      "price":"3.5",
      "datecreated":"1535216400",
      "status":"1",
      "tendangnhap":"dmvn01"
   },
   {  
      "id":"271",
      "member_id":"76",
      "price":"50",
      "datecreated":"1535216400",
      "status":"1",
      "tendangnhap":"dmvn"
   },
   {  
      "id":"270",
      "member_id":"75",
      "price":"50",
      "datecreated":"1535216400",
      "status":"1",
      "tendangnhap":"global01"
   },
   {  
      "id":"269",
      "member_id":"74",
      "price":"50",
      "datecreated":"1535216400",
      "status":"1",
      "tendangnhap":"global"
   },
   {  
      "id":"268",
      "member_id":"73",
      "price":"50",
      "datecreated":"1535216400",
      "status":"1",
      "tendangnhap":"sampath"
   },
   {  
      "id":"267",
      "member_id":"72",
      "price":"50",
      "datecreated":"1535216400",
      "status":"1",
      "tendangnhap":"kapila"
   },
   {  
      "id":"266",
      "member_id":"71",
      "price":"50",
      "datecreated":"1535216400",
      "status":"1",
      "tendangnhap":"vignessri"
   },
   {  
      "id":"265",
      "member_id":"70",
      "price":"50",
      "datecreated":"1535216400",
      "status":"1",
      "tendangnhap":"srilankadiamond"
   },
   {  
      "id":"264",
      "member_id":"1",
      "price":"600",
      "datecreated":"1535216400",
      "status":"1",
      "tendangnhap":"00000001"
   },
   {  
      "id":"263",
      "member_id":"105",
      "price":"1.5",
      "datecreated":"1535130000",
      "status":"1",
      "tendangnhap":"globalteam"
   },
   {  
      "id":"262",
      "member_id":"98",
      "price":"12",
      "datecreated":"1535130000",
      "status":"1",
      "tendangnhap":"sontyphu"
   },
   {  
      "id":"261",
      "member_id":"97",
      "price":"3.5",
      "datecreated":"1535130000",
      "status":"1",
      "tendangnhap":"Dmbd01"
   },
   {  
      "id":"260",
      "member_id":"96",
      "price":"1.5",
      "datecreated":"1535130000",
      "status":"1",
      "tendangnhap":"nguyenanbtc"
   },
   {  
      "id":"259",
      "member_id":"95",
      "price":"3.5",
      "datecreated":"1535130000",
      "status":"1",
      "tendangnhap":"trieuphuusd"
   },
   {  
      "id":"258",
      "member_id":"94",
      "price":"3.5",
      "datecreated":"1535130000",
      "status":"1",
      "tendangnhap":"typhu3"
   },
   {  
      "id":"257",
      "member_id":"91",
      "price":"1.8",
      "datecreated":"1535130000",
      "status":"1",
      "tendangnhap":"typhu"
   },
   {  
      "id":"256",
      "member_id":"90",
      "price":"50",
      "datecreated":"1535130000",
      "status":"1",
      "tendangnhap":"hecjes"
   },
   {  
      "id":"255",
      "member_id":"89",
      "price":"3.5",
      "datecreated":"1535130000",
      "status":"1",
      "tendangnhap":"ruwan"
   },
   {  
      "id":"254",
      "member_id":"88",
      "price":"3.5",
      "datecreated":"1535130000",
      "status":"1",
      "tendangnhap":"carlo"
   },
   {  
      "id":"253",
      "member_id":"87",
      "price":"3.5",
      "datecreated":"1535130000",
      "status":"1",
      "tendangnhap":"sarath"
   },
   {  
      "id":"252",
      "member_id":"86",
      "price":"3.5",
      "datecreated":"1535130000",
      "status":"1",
      "tendangnhap":"nimal"
   },
   {  
      "id":"251",
      "member_id":"85",
      "price":"3.5",
      "datecreated":"1535130000",
      "status":"1",
      "tendangnhap":"mahinda"
   },
   {  
      "id":"250",
      "member_id":"84",
      "price":"3.5",
      "datecreated":"1535130000",
      "status":"1",
      "tendangnhap":"chaminda"
   },
   {  
      "id":"249",
      "member_id":"83",
      "price":"3.5",
      "datecreated":"1535130000",
      "status":"1",
      "tendangnhap":"dmvn03"
   },
   {  
      "id":"248",
      "member_id":"82",
      "price":"3.5",
      "datecreated":"1535130000",
      "status":"1",
      "tendangnhap":"dmvn02"
   },
   {  
      "id":"247",
      "member_id":"81",
      "price":"3.5",
      "datecreated":"1535130000",
      "status":"1",
      "tendangnhap":"dmvn01"
   },
   {  
      "id":"246",
      "member_id":"76",
      "price":"50",
      "datecreated":"1535130000",
      "status":"1",
      "tendangnhap":"dmvn"
   },
   {  
      "id":"245",
      "member_id":"75",
      "price":"50",
      "datecreated":"1535130000",
      "status":"1",
      "tendangnhap":"global01"
   },
   {  
      "id":"244",
      "member_id":"74",
      "price":"50",
      "datecreated":"1535130000",
      "status":"1",
      "tendangnhap":"global"
   },
   {  
      "id":"243",
      "member_id":"73",
      "price":"50",
      "datecreated":"1535130000",
      "status":"1",
      "tendangnhap":"sampath"
   },
   {  
      "id":"242",
      "member_id":"72",
      "price":"50",
      "datecreated":"1535130000",
      "status":"1",
      "tendangnhap":"kapila"
   },
   {  
      "id":"241",
      "member_id":"71",
      "price":"50",
      "datecreated":"1535130000",
      "status":"1",
      "tendangnhap":"vignessri"
   },
   {  
      "id":"240",
      "member_id":"70",
      "price":"50",
      "datecreated":"1535130000",
      "status":"1",
      "tendangnhap":"srilankadiamond"
   },
   {  
      "id":"239",
      "member_id":"1",
      "price":"600",
      "datecreated":"1535130000",
      "status":"1",
      "tendangnhap":"00000001"
   },
   {  
      "id":"230",
      "member_id":"105",
      "price":"1.5",
      "datecreated":"1535043600",
      "status":"1",
      "tendangnhap":"globalteam"
   },
   {  
      "id":"229",
      "member_id":"98",
      "price":"12",
      "datecreated":"1535043600",
      "status":"1",
      "tendangnhap":"sontyphu"
   },
   {  
      "id":"228",
      "member_id":"97",
      "price":"3.5",
      "datecreated":"1535043600",
      "status":"1",
      "tendangnhap":"Dmbd01"
   },
   {  
      "id":"227",
      "member_id":"96",
      "price":"1.5",
      "datecreated":"1535043600",
      "status":"1",
      "tendangnhap":"nguyenanbtc"
   },
   {  
      "id":"226",
      "member_id":"95",
      "price":"3.5",
      "datecreated":"1535043600",
      "status":"1",
      "tendangnhap":"trieuphuusd"
   },
   {  
      "id":"225",
      "member_id":"94",
      "price":"3.5",
      "datecreated":"1535043600",
      "status":"1",
      "tendangnhap":"typhu3"
   },
   {  
      "id":"224",
      "member_id":"90",
      "price":"50",
      "datecreated":"1535043600",
      "status":"1",
      "tendangnhap":"hecjes"
   },
   {  
      "id":"223",
      "member_id":"89",
      "price":"3.5",
      "datecreated":"1535043600",
      "status":"1",
      "tendangnhap":"ruwan"
   },
   {  
      "id":"222",
      "member_id":"88",
      "price":"3.5",
      "datecreated":"1535043600",
      "status":"1",
      "tendangnhap":"carlo"
   },
   {  
      "id":"221",
      "member_id":"87",
      "price":"3.5",
      "datecreated":"1535043600",
      "status":"1",
      "tendangnhap":"sarath"
   },
   {  
      "id":"220",
      "member_id":"86",
      "price":"3.5",
      "datecreated":"1535043600",
      "status":"1",
      "tendangnhap":"nimal"
   },
   {  
      "id":"219",
      "member_id":"85",
      "price":"3.5",
      "datecreated":"1535043600",
      "status":"1",
      "tendangnhap":"mahinda"
   },
   {  
      "id":"218",
      "member_id":"84",
      "price":"3.5",
      "datecreated":"1535043600",
      "status":"1",
      "tendangnhap":"chaminda"
   },
   {  
      "id":"217",
      "member_id":"83",
      "price":"3.5",
      "datecreated":"1535043600",
      "status":"1",
      "tendangnhap":"dmvn03"
   },
   {  
      "id":"216",
      "member_id":"82",
      "price":"3.5",
      "datecreated":"1535043600",
      "status":"1",
      "tendangnhap":"dmvn02"
   },
   {  
      "id":"215",
      "member_id":"81",
      "price":"3.5",
      "datecreated":"1535043600",
      "status":"1",
      "tendangnhap":"dmvn01"
   },
   {  
      "id":"214",
      "member_id":"76",
      "price":"50",
      "datecreated":"1535043600",
      "status":"1",
      "tendangnhap":"dmvn"
   },
   {  
      "id":"213",
      "member_id":"75",
      "price":"50",
      "datecreated":"1535043600",
      "status":"1",
      "tendangnhap":"global01"
   },
   {  
      "id":"212",
      "member_id":"74",
      "price":"50",
      "datecreated":"1535043600",
      "status":"1",
      "tendangnhap":"global"
   },
   {  
      "id":"211",
      "member_id":"73",
      "price":"50",
      "datecreated":"1535043600",
      "status":"1",
      "tendangnhap":"sampath"
   },
   {  
      "id":"210",
      "member_id":"72",
      "price":"50",
      "datecreated":"1535043600",
      "status":"1",
      "tendangnhap":"kapila"
   },
   {  
      "id":"209",
      "member_id":"71",
      "price":"50",
      "datecreated":"1535043600",
      "status":"1",
      "tendangnhap":"vignessri"
   },
   {  
      "id":"208",
      "member_id":"70",
      "price":"50",
      "datecreated":"1535043600",
      "status":"1",
      "tendangnhap":"srilankadiamond"
   },
   {  
      "id":"207",
      "member_id":"1",
      "price":"600",
      "datecreated":"1535043600",
      "status":"1",
      "tendangnhap":"00000001"
   },
   {  
      "id":"206",
      "member_id":"98",
      "price":"12",
      "datecreated":"1534957200",
      "status":"1",
      "tendangnhap":"sontyphu"
   },
   {  
      "id":"205",
      "member_id":"97",
      "price":"3.5",
      "datecreated":"1534957200",
      "status":"1",
      "tendangnhap":"Dmbd01"
   },
   {  
      "id":"204",
      "member_id":"96",
      "price":"1.5",
      "datecreated":"1534957200",
      "status":"1",
      "tendangnhap":"nguyenanbtc"
   },
   {  
      "id":"203",
      "member_id":"95",
      "price":"3.5",
      "datecreated":"1534957200",
      "status":"1",
      "tendangnhap":"trieuphuusd"
   },
   {  
      "id":"202",
      "member_id":"94",
      "price":"3.5",
      "datecreated":"1534957200",
      "status":"1",
      "tendangnhap":"typhu3"
   },
   {  
      "id":"201",
      "member_id":"90",
      "price":"50",
      "datecreated":"1534957200",
      "status":"1",
      "tendangnhap":"hecjes"
   },
   {  
      "id":"200",
      "member_id":"89",
      "price":"3.5",
      "datecreated":"1534957200",
      "status":"1",
      "tendangnhap":"ruwan"
   },
   {  
      "id":"199",
      "member_id":"88",
      "price":"3.5",
      "datecreated":"1534957200",
      "status":"1",
      "tendangnhap":"carlo"
   },
   {  
      "id":"198",
      "member_id":"87",
      "price":"3.5",
      "datecreated":"1534957200",
      "status":"1",
      "tendangnhap":"sarath"
   },
   {  
      "id":"197",
      "member_id":"86",
      "price":"3.5",
      "datecreated":"1534957200",
      "status":"1",
      "tendangnhap":"nimal"
   },
   {  
      "id":"196",
      "member_id":"85",
      "price":"3.5",
      "datecreated":"1534957200",
      "status":"1",
      "tendangnhap":"mahinda"
   },
   {  
      "id":"195",
      "member_id":"84",
      "price":"3.5",
      "datecreated":"1534957200",
      "status":"1",
      "tendangnhap":"chaminda"
   },
   {  
      "id":"194",
      "member_id":"83",
      "price":"3.5",
      "datecreated":"1534957200",
      "status":"1",
      "tendangnhap":"dmvn03"
   },
   {  
      "id":"193",
      "member_id":"82",
      "price":"3.5",
      "datecreated":"1534957200",
      "status":"1",
      "tendangnhap":"dmvn02"
   },
   {  
      "id":"192",
      "member_id":"81",
      "price":"3.5",
      "datecreated":"1534957200",
      "status":"1",
      "tendangnhap":"dmvn01"
   },
   {  
      "id":"191",
      "member_id":"76",
      "price":"50",
      "datecreated":"1534957200",
      "status":"1",
      "tendangnhap":"dmvn"
   },
   {  
      "id":"190",
      "member_id":"75",
      "price":"50",
      "datecreated":"1534957200",
      "status":"1",
      "tendangnhap":"global01"
   },
   {  
      "id":"189",
      "member_id":"74",
      "price":"50",
      "datecreated":"1534957200",
      "status":"1",
      "tendangnhap":"global"
   },
   {  
      "id":"188",
      "member_id":"73",
      "price":"50",
      "datecreated":"1534957200",
      "status":"1",
      "tendangnhap":"sampath"
   },
   {  
      "id":"187",
      "member_id":"72",
      "price":"50",
      "datecreated":"1534957200",
      "status":"1",
      "tendangnhap":"kapila"
   },
   {  
      "id":"186",
      "member_id":"71",
      "price":"50",
      "datecreated":"1534957200",
      "status":"1",
      "tendangnhap":"vignessri"
   },
   {  
      "id":"185",
      "member_id":"70",
      "price":"50",
      "datecreated":"1534957200",
      "status":"1",
      "tendangnhap":"srilankadiamond"
   },
   {  
      "id":"184",
      "member_id":"1",
      "price":"600",
      "datecreated":"1534957200",
      "status":"1",
      "tendangnhap":"00000001"
   },
   {  
      "id":"183",
      "member_id":"76",
      "price":"50",
      "datecreated":"1534870800",
      "status":"1",
      "tendangnhap":"dmvn"
   },
   {  
      "id":"182",
      "member_id":"75",
      "price":"50",
      "datecreated":"1534870800",
      "status":"1",
      "tendangnhap":"global01"
   },
   {  
      "id":"181",
      "member_id":"74",
      "price":"50",
      "datecreated":"1534870800",
      "status":"1",
      "tendangnhap":"global"
   },
   {  
      "id":"180",
      "member_id":"73",
      "price":"50",
      "datecreated":"1534870800",
      "status":"1",
      "tendangnhap":"sampath"
   },
   {  
      "id":"179",
      "member_id":"72",
      "price":"50",
      "datecreated":"1534870800",
      "status":"1",
      "tendangnhap":"kapila"
   },
   {  
      "id":"178",
      "member_id":"71",
      "price":"50",
      "datecreated":"1534870800",
      "status":"1",
      "tendangnhap":"vignessri"
   },
   {  
      "id":"177",
      "member_id":"70",
      "price":"50",
      "datecreated":"1534870800",
      "status":"1",
      "tendangnhap":"srilankadiamond"
   },
   {  
      "id":"176",
      "member_id":"1",
      "price":"600",
      "datecreated":"1534870800",
      "status":"1",
      "tendangnhap":"00000001"
   },
   {  
      "id":"273",
      "member_id":"82",
      "price":"3.5",
      "datecreated":"1535216400",
      "status":"1",
      "tendangnhap":"dmvn02"
   },
   {  
      "id":"274",
      "member_id":"83",
      "price":"3.5",
      "datecreated":"1535216400",
      "status":"1",
      "tendangnhap":"dmvn03"
   },
   {  
      "id":"275",
      "member_id":"84",
      "price":"3.5",
      "datecreated":"1535216400",
      "status":"1",
      "tendangnhap":"chaminda"
   },
   {  
      "id":"276",
      "member_id":"85",
      "price":"3.5",
      "datecreated":"1535216400",
      "status":"1",
      "tendangnhap":"mahinda"
   },
   {  
      "id":"277",
      "member_id":"86",
      "price":"3.5",
      "datecreated":"1535216400",
      "status":"1",
      "tendangnhap":"nimal"
   },
   {  
      "id":"278",
      "member_id":"87",
      "price":"3.5",
      "datecreated":"1535216400",
      "status":"1",
      "tendangnhap":"sarath"
   },
   {  
      "id":"279",
      "member_id":"88",
      "price":"3.5",
      "datecreated":"1535216400",
      "status":"1",
      "tendangnhap":"carlo"
   },
   {  
      "id":"280",
      "member_id":"89",
      "price":"3.5",
      "datecreated":"1535216400",
      "status":"1",
      "tendangnhap":"ruwan"
   },
   {  
      "id":"281",
      "member_id":"90",
      "price":"50",
      "datecreated":"1535216400",
      "status":"1",
      "tendangnhap":"hecjes"
   },
   {  
      "id":"282",
      "member_id":"91",
      "price":"1.8",
      "datecreated":"1535216400",
      "status":"1",
      "tendangnhap":"typhu"
   },
   {  
      "id":"283",
      "member_id":"94",
      "price":"3.5",
      "datecreated":"1535216400",
      "status":"1",
      "tendangnhap":"typhu3"
   },
   {  
      "id":"284",
      "member_id":"95",
      "price":"3.5",
      "datecreated":"1535216400",
      "status":"1",
      "tendangnhap":"trieuphuusd"
   },
   {  
      "id":"285",
      "member_id":"96",
      "price":"1.5",
      "datecreated":"1535216400",
      "status":"1",
      "tendangnhap":"nguyenanbtc"
   },
   {  
      "id":"286",
      "member_id":"97",
      "price":"3.5",
      "datecreated":"1535216400",
      "status":"1",
      "tendangnhap":"Dmbd01"
   },
   {  
      "id":"287",
      "member_id":"98",
      "price":"12",
      "datecreated":"1535216400",
      "status":"1",
      "tendangnhap":"sontyphu"
   },
   {  
      "id":"288",
      "member_id":"105",
      "price":"1.5",
      "datecreated":"1535216400",
      "status":"1",
      "tendangnhap":"globalteam"
   },
   {  
      "id":"289",
      "member_id":"1",
      "price":"600",
      "datecreated":"1535302800",
      "status":"1",
      "tendangnhap":"00000001"
   },
   {  
      "id":"290",
      "member_id":"70",
      "price":"50",
      "datecreated":"1535302800",
      "status":"1",
      "tendangnhap":"srilankadiamond"
   },
   {  
      "id":"291",
      "member_id":"71",
      "price":"50",
      "datecreated":"1535302800",
      "status":"1",
      "tendangnhap":"vignessri"
   },
   {  
      "id":"292",
      "member_id":"72",
      "price":"50",
      "datecreated":"1535302800",
      "status":"1",
      "tendangnhap":"kapila"
   },
   {  
      "id":"293",
      "member_id":"73",
      "price":"50",
      "datecreated":"1535302800",
      "status":"1",
      "tendangnhap":"sampath"
   },
   {  
      "id":"294",
      "member_id":"74",
      "price":"50",
      "datecreated":"1535302800",
      "status":"1",
      "tendangnhap":"global"
   },
   {  
      "id":"295",
      "member_id":"75",
      "price":"50",
      "datecreated":"1535302800",
      "status":"1",
      "tendangnhap":"global01"
   },
   {  
      "id":"296",
      "member_id":"76",
      "price":"50",
      "datecreated":"1535302800",
      "status":"1",
      "tendangnhap":"dmvn"
   },
   {  
      "id":"297",
      "member_id":"81",
      "price":"3.5",
      "datecreated":"1535302800",
      "status":"1",
      "tendangnhap":"dmvn01"
   },
   {  
      "id":"298",
      "member_id":"82",
      "price":"3.5",
      "datecreated":"1535302800",
      "status":"1",
      "tendangnhap":"dmvn02"
   },
   {  
      "id":"299",
      "member_id":"83",
      "price":"3.5",
      "datecreated":"1535302800",
      "status":"1",
      "tendangnhap":"dmvn03"
   },
   {  
      "id":"300",
      "member_id":"84",
      "price":"3.5",
      "datecreated":"1535302800",
      "status":"1",
      "tendangnhap":"chaminda"
   },
   {  
      "id":"301",
      "member_id":"85",
      "price":"3.5",
      "datecreated":"1535302800",
      "status":"1",
      "tendangnhap":"mahinda"
   },
   {  
      "id":"302",
      "member_id":"86",
      "price":"3.5",
      "datecreated":"1535302800",
      "status":"1",
      "tendangnhap":"nimal"
   },
   {  
      "id":"303",
      "member_id":"87",
      "price":"3.5",
      "datecreated":"1535302800",
      "status":"1",
      "tendangnhap":"sarath"
   },
   {  
      "id":"304",
      "member_id":"88",
      "price":"3.5",
      "datecreated":"1535302800",
      "status":"1",
      "tendangnhap":"carlo"
   },
   {  
      "id":"305",
      "member_id":"89",
      "price":"3.5",
      "datecreated":"1535302800",
      "status":"1",
      "tendangnhap":"ruwan"
   },
   {  
      "id":"306",
      "member_id":"90",
      "price":"50",
      "datecreated":"1535302800",
      "status":"1",
      "tendangnhap":"hecjes"
   },
   {  
      "id":"307",
      "member_id":"91",
      "price":"1.8",
      "datecreated":"1535302800",
      "status":"1",
      "tendangnhap":"typhu"
   },
   {  
      "id":"308",
      "member_id":"94",
      "price":"3.5",
      "datecreated":"1535302800",
      "status":"1",
      "tendangnhap":"typhu3"
   },
   {  
      "id":"309",
      "member_id":"95",
      "price":"3.5",
      "datecreated":"1535302800",
      "status":"1",
      "tendangnhap":"trieuphuusd"
   },
   {  
      "id":"310",
      "member_id":"96",
      "price":"1.5",
      "datecreated":"1535302800",
      "status":"1",
      "tendangnhap":"nguyenanbtc"
   },
   {  
      "id":"311",
      "member_id":"97",
      "price":"3.5",
      "datecreated":"1535302800",
      "status":"1",
      "tendangnhap":"Dmbd01"
   },
   {  
      "id":"312",
      "member_id":"98",
      "price":"12",
      "datecreated":"1535302800",
      "status":"1",
      "tendangnhap":"sontyphu"
   },
   {  
      "id":"313",
      "member_id":"105",
      "price":"1.5",
      "datecreated":"1535302800",
      "status":"1",
      "tendangnhap":"globalteam"
   },
   {  
      "id":"314",
      "member_id":"1",
      "price":"600",
      "datecreated":"1535389200",
      "status":"1",
      "tendangnhap":"00000001"
   },
   {  
      "id":"315",
      "member_id":"70",
      "price":"50",
      "datecreated":"1535389200",
      "status":"1",
      "tendangnhap":"srilankadiamond"
   },
   {  
      "id":"316",
      "member_id":"71",
      "price":"50",
      "datecreated":"1535389200",
      "status":"1",
      "tendangnhap":"vignessri"
   },
   {  
      "id":"317",
      "member_id":"72",
      "price":"50",
      "datecreated":"1535389200",
      "status":"1",
      "tendangnhap":"kapila"
   },
   {  
      "id":"318",
      "member_id":"73",
      "price":"50",
      "datecreated":"1535389200",
      "status":"1",
      "tendangnhap":"sampath"
   },
   {  
      "id":"319",
      "member_id":"74",
      "price":"50",
      "datecreated":"1535389200",
      "status":"1",
      "tendangnhap":"global"
   },
   {  
      "id":"320",
      "member_id":"75",
      "price":"50",
      "datecreated":"1535389200",
      "status":"1",
      "tendangnhap":"global01"
   },
   {  
      "id":"321",
      "member_id":"76",
      "price":"50",
      "datecreated":"1535389200",
      "status":"1",
      "tendangnhap":"dmvn"
   },
   {  
      "id":"322",
      "member_id":"81",
      "price":"3.5",
      "datecreated":"1535389200",
      "status":"1",
      "tendangnhap":"dmvn01"
   },
   {  
      "id":"323",
      "member_id":"82",
      "price":"3.5",
      "datecreated":"1535389200",
      "status":"1",
      "tendangnhap":"dmvn02"
   },
   {  
      "id":"324",
      "member_id":"83",
      "price":"3.5",
      "datecreated":"1535389200",
      "status":"1",
      "tendangnhap":"dmvn03"
   },
   {  
      "id":"325",
      "member_id":"84",
      "price":"3.5",
      "datecreated":"1535389200",
      "status":"1",
      "tendangnhap":"chaminda"
   },
   {  
      "id":"326",
      "member_id":"85",
      "price":"3.5",
      "datecreated":"1535389200",
      "status":"1",
      "tendangnhap":"mahinda"
   },
   {  
      "id":"327",
      "member_id":"86",
      "price":"3.5",
      "datecreated":"1535389200",
      "status":"1",
      "tendangnhap":"nimal"
   },
   {  
      "id":"328",
      "member_id":"87",
      "price":"3.5",
      "datecreated":"1535389200",
      "status":"1",
      "tendangnhap":"sarath"
   },
   {  
      "id":"329",
      "member_id":"88",
      "price":"3.5",
      "datecreated":"1535389200",
      "status":"1",
      "tendangnhap":"carlo"
   },
   {  
      "id":"330",
      "member_id":"89",
      "price":"3.5",
      "datecreated":"1535389200",
      "status":"1",
      "tendangnhap":"ruwan"
   },
   {  
      "id":"331",
      "member_id":"90",
      "price":"50",
      "datecreated":"1535389200",
      "status":"1",
      "tendangnhap":"hecjes"
   },
   {  
      "id":"332",
      "member_id":"91",
      "price":"1.8",
      "datecreated":"1535389200",
      "status":"1",
      "tendangnhap":"typhu"
   },
   {  
      "id":"333",
      "member_id":"94",
      "price":"3.5",
      "datecreated":"1535389200",
      "status":"1",
      "tendangnhap":"typhu3"
   },
   {  
      "id":"334",
      "member_id":"95",
      "price":"3.5",
      "datecreated":"1535389200",
      "status":"1",
      "tendangnhap":"trieuphuusd"
   },
   {  
      "id":"335",
      "member_id":"96",
      "price":"1.5",
      "datecreated":"1535389200",
      "status":"1",
      "tendangnhap":"nguyenanbtc"
   },
   {  
      "id":"336",
      "member_id":"97",
      "price":"3.5",
      "datecreated":"1535389200",
      "status":"1",
      "tendangnhap":"Dmbd01"
   },
   {  
      "id":"337",
      "member_id":"98",
      "price":"12",
      "datecreated":"1535389200",
      "status":"1",
      "tendangnhap":"sontyphu"
   },
   {  
      "id":"338",
      "member_id":"105",
      "price":"1.5",
      "datecreated":"1535389200",
      "status":"1",
      "tendangnhap":"globalteam"
   },
   {  
      "id":"339",
      "member_id":"106",
      "price":"3.5",
      "datecreated":"1535389200",
      "status":"1",
      "tendangnhap":"Dmsg"
   },
   {  
      "id":"340",
      "member_id":"108",
      "price":"3.5",
      "datecreated":"1535389200",
      "status":"1",
      "tendangnhap":"Thanhconguv"
   },
   {  
      "id":"341",
      "member_id":"109",
      "price":"50",
      "datecreated":"1535389200",
      "status":"1",
      "tendangnhap":"winwin2018"
   },
   {  
      "id":"342",
      "member_id":"1",
      "price":"600",
      "datecreated":"1535475600",
      "status":"1",
      "tendangnhap":"00000001"
   },
   {  
      "id":"343",
      "member_id":"70",
      "price":"50",
      "datecreated":"1535475600",
      "status":"1",
      "tendangnhap":"srilankadiamond"
   },
   {  
      "id":"344",
      "member_id":"71",
      "price":"50",
      "datecreated":"1535475600",
      "status":"1",
      "tendangnhap":"vignessri"
   },
   {  
      "id":"345",
      "member_id":"72",
      "price":"50",
      "datecreated":"1535475600",
      "status":"1",
      "tendangnhap":"kapila"
   },
   {  
      "id":"346",
      "member_id":"73",
      "price":"50",
      "datecreated":"1535475600",
      "status":"1",
      "tendangnhap":"sampath"
   },
   {  
      "id":"347",
      "member_id":"74",
      "price":"50",
      "datecreated":"1535475600",
      "status":"1",
      "tendangnhap":"global"
   },
   {  
      "id":"348",
      "member_id":"75",
      "price":"50",
      "datecreated":"1535475600",
      "status":"1",
      "tendangnhap":"global01"
   },
   {  
      "id":"349",
      "member_id":"76",
      "price":"50",
      "datecreated":"1535475600",
      "status":"1",
      "tendangnhap":"dmvn"
   },
   {  
      "id":"350",
      "member_id":"81",
      "price":"3.5",
      "datecreated":"1535475600",
      "status":"1",
      "tendangnhap":"dmvn01"
   },
   {  
      "id":"351",
      "member_id":"82",
      "price":"3.5",
      "datecreated":"1535475600",
      "status":"1",
      "tendangnhap":"dmvn02"
   },
   {  
      "id":"352",
      "member_id":"83",
      "price":"3.5",
      "datecreated":"1535475600",
      "status":"1",
      "tendangnhap":"dmvn03"
   },
   {  
      "id":"353",
      "member_id":"84",
      "price":"3.5",
      "datecreated":"1535475600",
      "status":"1",
      "tendangnhap":"chaminda"
   },
   {  
      "id":"354",
      "member_id":"85",
      "price":"3.5",
      "datecreated":"1535475600",
      "status":"1",
      "tendangnhap":"mahinda"
   },
   {  
      "id":"355",
      "member_id":"86",
      "price":"3.5",
      "datecreated":"1535475600",
      "status":"1",
      "tendangnhap":"nimal"
   },
   {  
      "id":"356",
      "member_id":"87",
      "price":"3.5",
      "datecreated":"1535475600",
      "status":"1",
      "tendangnhap":"sarath"
   },
   {  
      "id":"357",
      "member_id":"88",
      "price":"3.5",
      "datecreated":"1535475600",
      "status":"1",
      "tendangnhap":"carlo"
   },
   {  
      "id":"358",
      "member_id":"89",
      "price":"3.5",
      "datecreated":"1535475600",
      "status":"1",
      "tendangnhap":"ruwan"
   },
   {  
      "id":"359",
      "member_id":"90",
      "price":"50",
      "datecreated":"1535475600",
      "status":"1",
      "tendangnhap":"hecjes"
   },
   {  
      "id":"360",
      "member_id":"91",
      "price":"1.8",
      "datecreated":"1535475600",
      "status":"1",
      "tendangnhap":"typhu"
   },
   {  
      "id":"361",
      "member_id":"94",
      "price":"3.5",
      "datecreated":"1535475600",
      "status":"1",
      "tendangnhap":"typhu3"
   },
   {  
      "id":"362",
      "member_id":"95",
      "price":"3.5",
      "datecreated":"1535475600",
      "status":"1",
      "tendangnhap":"trieuphuusd"
   },
   {  
      "id":"363",
      "member_id":"96",
      "price":"1.5",
      "datecreated":"1535475600",
      "status":"1",
      "tendangnhap":"nguyenanbtc"
   },
   {  
      "id":"364",
      "member_id":"97",
      "price":"3.5",
      "datecreated":"1535475600",
      "status":"1",
      "tendangnhap":"Dmbd01"
   },
   {  
      "id":"365",
      "member_id":"98",
      "price":"12",
      "datecreated":"1535475600",
      "status":"1",
      "tendangnhap":"sontyphu"
   },
   {  
      "id":"366",
      "member_id":"105",
      "price":"1.5",
      "datecreated":"1535475600",
      "status":"1",
      "tendangnhap":"globalteam"
   },
   {  
      "id":"367",
      "member_id":"106",
      "price":"3.5",
      "datecreated":"1535475600",
      "status":"1",
      "tendangnhap":"Dmsg"
   },
   {  
      "id":"368",
      "member_id":"108",
      "price":"3.5",
      "datecreated":"1535475600",
      "status":"1",
      "tendangnhap":"Thanhconguv"
   },
   {  
      "id":"369",
      "member_id":"109",
      "price":"50",
      "datecreated":"1535475600",
      "status":"1",
      "tendangnhap":"winwin2018"
   },
   {  
      "id":"370",
      "member_id":"110",
      "price":"1.5",
      "datecreated":"1535475600",
      "status":"1",
      "tendangnhap":"winwin01"
   },
   {  
      "id":"371",
      "member_id":"111",
      "price":"1.5",
      "datecreated":"1535475600",
      "status":"1",
      "tendangnhap":"typhuhnvn"
   },
   {  
      "id":"372",
      "member_id":"112",
      "price":"1.5",
      "datecreated":"1535475600",
      "status":"1",
      "tendangnhap":"winwin02"
   },
   {  
      "id":"373",
      "member_id":"1",
      "price":"600",
      "datecreated":"1535562000",
      "status":"1",
      "tendangnhap":"00000001"
   },
   {  
      "id":"374",
      "member_id":"70",
      "price":"50",
      "datecreated":"1535562000",
      "status":"1",
      "tendangnhap":"srilankadiamond"
   },
   {  
      "id":"375",
      "member_id":"71",
      "price":"50",
      "datecreated":"1535562000",
      "status":"1",
      "tendangnhap":"vignessri"
   },
   {  
      "id":"376",
      "member_id":"72",
      "price":"50",
      "datecreated":"1535562000",
      "status":"1",
      "tendangnhap":"kapila"
   },
   {  
      "id":"377",
      "member_id":"73",
      "price":"50",
      "datecreated":"1535562000",
      "status":"1",
      "tendangnhap":"sampath"
   },
   {  
      "id":"378",
      "member_id":"74",
      "price":"50",
      "datecreated":"1535562000",
      "status":"1",
      "tendangnhap":"global"
   },
   {  
      "id":"379",
      "member_id":"75",
      "price":"50",
      "datecreated":"1535562000",
      "status":"1",
      "tendangnhap":"global01"
   },
   {  
      "id":"380",
      "member_id":"76",
      "price":"50",
      "datecreated":"1535562000",
      "status":"1",
      "tendangnhap":"dmvn"
   },
   {  
      "id":"381",
      "member_id":"81",
      "price":"3.5",
      "datecreated":"1535562000",
      "status":"1",
      "tendangnhap":"dmvn01"
   },
   {  
      "id":"382",
      "member_id":"82",
      "price":"3.5",
      "datecreated":"1535562000",
      "status":"1",
      "tendangnhap":"dmvn02"
   },
   {  
      "id":"383",
      "member_id":"83",
      "price":"3.5",
      "datecreated":"1535562000",
      "status":"1",
      "tendangnhap":"dmvn03"
   },
   {  
      "id":"384",
      "member_id":"84",
      "price":"3.5",
      "datecreated":"1535562000",
      "status":"1",
      "tendangnhap":"chaminda"
   },
   {  
      "id":"385",
      "member_id":"85",
      "price":"3.5",
      "datecreated":"1535562000",
      "status":"1",
      "tendangnhap":"mahinda"
   },
   {  
      "id":"386",
      "member_id":"86",
      "price":"3.5",
      "datecreated":"1535562000",
      "status":"1",
      "tendangnhap":"nimal"
   },
   {  
      "id":"387",
      "member_id":"87",
      "price":"3.5",
      "datecreated":"1535562000",
      "status":"1",
      "tendangnhap":"sarath"
   },
   {  
      "id":"388",
      "member_id":"88",
      "price":"3.5",
      "datecreated":"1535562000",
      "status":"1",
      "tendangnhap":"carlo"
   },
   {  
      "id":"389",
      "member_id":"89",
      "price":"3.5",
      "datecreated":"1535562000",
      "status":"1",
      "tendangnhap":"ruwan"
   },
   {  
      "id":"390",
      "member_id":"90",
      "price":"50",
      "datecreated":"1535562000",
      "status":"1",
      "tendangnhap":"hecjes"
   },
   {  
      "id":"391",
      "member_id":"91",
      "price":"1.8",
      "datecreated":"1535562000",
      "status":"1",
      "tendangnhap":"typhu"
   },
   {  
      "id":"392",
      "member_id":"94",
      "price":"3.5",
      "datecreated":"1535562000",
      "status":"1",
      "tendangnhap":"typhu3"
   },
   {  
      "id":"393",
      "member_id":"95",
      "price":"3.5",
      "datecreated":"1535562000",
      "status":"1",
      "tendangnhap":"trieuphuusd"
   },
   {  
      "id":"394",
      "member_id":"96",
      "price":"1.5",
      "datecreated":"1535562000",
      "status":"1",
      "tendangnhap":"nguyenanbtc"
   },
   {  
      "id":"395",
      "member_id":"97",
      "price":"3.5",
      "datecreated":"1535562000",
      "status":"1",
      "tendangnhap":"Dmbd01"
   },
   {  
      "id":"396",
      "member_id":"98",
      "price":"12",
      "datecreated":"1535562000",
      "status":"1",
      "tendangnhap":"sontyphu"
   },
   {  
      "id":"397",
      "member_id":"105",
      "price":"1.5",
      "datecreated":"1535562000",
      "status":"1",
      "tendangnhap":"globalteam"
   },
   {  
      "id":"398",
      "member_id":"106",
      "price":"3.5",
      "datecreated":"1535562000",
      "status":"1",
      "tendangnhap":"Dmsg"
   },
   {  
      "id":"399",
      "member_id":"108",
      "price":"3.5",
      "datecreated":"1535562000",
      "status":"1",
      "tendangnhap":"Thanhconguv"
   },
   {  
      "id":"400",
      "member_id":"109",
      "price":"50",
      "datecreated":"1535562000",
      "status":"1",
      "tendangnhap":"winwin2018"
   },
   {  
      "id":"401",
      "member_id":"110",
      "price":"1.5",
      "datecreated":"1535562000",
      "status":"1",
      "tendangnhap":"winwin01"
   },
   {  
      "id":"402",
      "member_id":"111",
      "price":"1.5",
      "datecreated":"1535562000",
      "status":"1",
      "tendangnhap":"typhuhnvn"
   },
   {  
      "id":"403",
      "member_id":"112",
      "price":"1.5",
      "datecreated":"1535562000",
      "status":"1",
      "tendangnhap":"winwin02"
   },
   {  
      "id":"404",
      "member_id":"1",
      "price":"600",
      "datecreated":"1535648400",
      "status":"1",
      "tendangnhap":"00000001"
   },
   {  
      "id":"405",
      "member_id":"70",
      "price":"50",
      "datecreated":"1535648400",
      "status":"1",
      "tendangnhap":"srilankadiamond"
   },
   {  
      "id":"406",
      "member_id":"71",
      "price":"50",
      "datecreated":"1535648400",
      "status":"1",
      "tendangnhap":"vignessri"
   },
   {  
      "id":"407",
      "member_id":"72",
      "price":"50",
      "datecreated":"1535648400",
      "status":"1",
      "tendangnhap":"kapila"
   },
   {  
      "id":"408",
      "member_id":"73",
      "price":"50",
      "datecreated":"1535648400",
      "status":"1",
      "tendangnhap":"sampath"
   },
   {  
      "id":"409",
      "member_id":"74",
      "price":"50",
      "datecreated":"1535648400",
      "status":"1",
      "tendangnhap":"global"
   },
   {  
      "id":"410",
      "member_id":"75",
      "price":"50",
      "datecreated":"1535648400",
      "status":"1",
      "tendangnhap":"global01"
   },
   {  
      "id":"411",
      "member_id":"76",
      "price":"50",
      "datecreated":"1535648400",
      "status":"1",
      "tendangnhap":"dmvn"
   },
   {  
      "id":"412",
      "member_id":"81",
      "price":"3.5",
      "datecreated":"1535648400",
      "status":"1",
      "tendangnhap":"dmvn01"
   },
   {  
      "id":"413",
      "member_id":"82",
      "price":"3.5",
      "datecreated":"1535648400",
      "status":"1",
      "tendangnhap":"dmvn02"
   },
   {  
      "id":"414",
      "member_id":"83",
      "price":"3.5",
      "datecreated":"1535648400",
      "status":"1",
      "tendangnhap":"dmvn03"
   },
   {  
      "id":"415",
      "member_id":"84",
      "price":"3.5",
      "datecreated":"1535648400",
      "status":"1",
      "tendangnhap":"chaminda"
   },
   {  
      "id":"416",
      "member_id":"85",
      "price":"3.5",
      "datecreated":"1535648400",
      "status":"1",
      "tendangnhap":"mahinda"
   },
   {  
      "id":"417",
      "member_id":"86",
      "price":"3.5",
      "datecreated":"1535648400",
      "status":"1",
      "tendangnhap":"nimal"
   },
   {  
      "id":"418",
      "member_id":"87",
      "price":"3.5",
      "datecreated":"1535648400",
      "status":"1",
      "tendangnhap":"sarath"
   },
   {  
      "id":"419",
      "member_id":"88",
      "price":"3.5",
      "datecreated":"1535648400",
      "status":"1",
      "tendangnhap":"carlo"
   },
   {  
      "id":"420",
      "member_id":"89",
      "price":"3.5",
      "datecreated":"1535648400",
      "status":"1",
      "tendangnhap":"ruwan"
   },
   {  
      "id":"421",
      "member_id":"90",
      "price":"50",
      "datecreated":"1535648400",
      "status":"1",
      "tendangnhap":"hecjes"
   },
   {  
      "id":"422",
      "member_id":"91",
      "price":"1.8",
      "datecreated":"1535648400",
      "status":"1",
      "tendangnhap":"typhu"
   },
   {  
      "id":"423",
      "member_id":"94",
      "price":"3.5",
      "datecreated":"1535648400",
      "status":"1",
      "tendangnhap":"typhu3"
   },
   {  
      "id":"424",
      "member_id":"95",
      "price":"3.5",
      "datecreated":"1535648400",
      "status":"1",
      "tendangnhap":"trieuphuusd"
   },
   {  
      "id":"425",
      "member_id":"96",
      "price":"1.5",
      "datecreated":"1535648400",
      "status":"1",
      "tendangnhap":"nguyenanbtc"
   },
   {  
      "id":"426",
      "member_id":"97",
      "price":"3.5",
      "datecreated":"1535648400",
      "status":"1",
      "tendangnhap":"Dmbd01"
   },
   {  
      "id":"427",
      "member_id":"98",
      "price":"12",
      "datecreated":"1535648400",
      "status":"1",
      "tendangnhap":"sontyphu"
   },
   {  
      "id":"428",
      "member_id":"105",
      "price":"1.5",
      "datecreated":"1535648400",
      "status":"1",
      "tendangnhap":"globalteam"
   },
   {  
      "id":"429",
      "member_id":"106",
      "price":"3.5",
      "datecreated":"1535648400",
      "status":"1",
      "tendangnhap":"Dmsg"
   },
   {  
      "id":"430",
      "member_id":"108",
      "price":"3.5",
      "datecreated":"1535648400",
      "status":"1",
      "tendangnhap":"Thanhconguv"
   },
   {  
      "id":"431",
      "member_id":"109",
      "price":"50",
      "datecreated":"1535648400",
      "status":"1",
      "tendangnhap":"winwin2018"
   },
   {  
      "id":"432",
      "member_id":"110",
      "price":"1.5",
      "datecreated":"1535648400",
      "status":"1",
      "tendangnhap":"winwin01"
   },
   {  
      "id":"433",
      "member_id":"111",
      "price":"1.5",
      "datecreated":"1535648400",
      "status":"1",
      "tendangnhap":"typhuhnvn"
   },
   {  
      "id":"434",
      "member_id":"112",
      "price":"1.5",
      "datecreated":"1535648400",
      "status":"1",
      "tendangnhap":"winwin02"
   },
   {  
      "id":"435",
      "member_id":"1",
      "price":"600",
      "datecreated":"1535734800",
      "status":"1",
      "tendangnhap":"00000001"
   },
   {  
      "id":"436",
      "member_id":"70",
      "price":"50",
      "datecreated":"1535734800",
      "status":"1",
      "tendangnhap":"srilankadiamond"
   },
   {  
      "id":"437",
      "member_id":"71",
      "price":"50",
      "datecreated":"1535734800",
      "status":"1",
      "tendangnhap":"vignessri"
   },
   {  
      "id":"438",
      "member_id":"72",
      "price":"50",
      "datecreated":"1535734800",
      "status":"1",
      "tendangnhap":"kapila"
   },
   {  
      "id":"439",
      "member_id":"73",
      "price":"50",
      "datecreated":"1535734800",
      "status":"1",
      "tendangnhap":"sampath"
   },
   {  
      "id":"440",
      "member_id":"74",
      "price":"50",
      "datecreated":"1535734800",
      "status":"1",
      "tendangnhap":"global"
   },
   {  
      "id":"441",
      "member_id":"75",
      "price":"50",
      "datecreated":"1535734800",
      "status":"1",
      "tendangnhap":"global01"
   },
   {  
      "id":"442",
      "member_id":"76",
      "price":"50",
      "datecreated":"1535734800",
      "status":"1",
      "tendangnhap":"dmvn"
   },
   {  
      "id":"443",
      "member_id":"81",
      "price":"3.5",
      "datecreated":"1535734800",
      "status":"1",
      "tendangnhap":"dmvn01"
   },
   {  
      "id":"444",
      "member_id":"82",
      "price":"3.5",
      "datecreated":"1535734800",
      "status":"1",
      "tendangnhap":"dmvn02"
   },
   {  
      "id":"445",
      "member_id":"83",
      "price":"3.5",
      "datecreated":"1535734800",
      "status":"1",
      "tendangnhap":"dmvn03"
   },
   {  
      "id":"446",
      "member_id":"84",
      "price":"3.5",
      "datecreated":"1535734800",
      "status":"1",
      "tendangnhap":"chaminda"
   },
   {  
      "id":"447",
      "member_id":"85",
      "price":"3.5",
      "datecreated":"1535734800",
      "status":"1",
      "tendangnhap":"mahinda"
   },
   {  
      "id":"448",
      "member_id":"86",
      "price":"3.5",
      "datecreated":"1535734800",
      "status":"1",
      "tendangnhap":"nimal"
   },
   {  
      "id":"449",
      "member_id":"87",
      "price":"3.5",
      "datecreated":"1535734800",
      "status":"1",
      "tendangnhap":"sarath"
   },
   {  
      "id":"450",
      "member_id":"88",
      "price":"3.5",
      "datecreated":"1535734800",
      "status":"1",
      "tendangnhap":"carlo"
   },
   {  
      "id":"451",
      "member_id":"89",
      "price":"3.5",
      "datecreated":"1535734800",
      "status":"1",
      "tendangnhap":"ruwan"
   },
   {  
      "id":"452",
      "member_id":"90",
      "price":"50",
      "datecreated":"1535734800",
      "status":"1",
      "tendangnhap":"hecjes"
   },
   {  
      "id":"453",
      "member_id":"91",
      "price":"1.8",
      "datecreated":"1535734800",
      "status":"1",
      "tendangnhap":"typhu"
   },
   {  
      "id":"454",
      "member_id":"94",
      "price":"3.5",
      "datecreated":"1535734800",
      "status":"1",
      "tendangnhap":"typhu3"
   },
   {  
      "id":"455",
      "member_id":"95",
      "price":"3.5",
      "datecreated":"1535734800",
      "status":"1",
      "tendangnhap":"trieuphuusd"
   },
   {  
      "id":"456",
      "member_id":"96",
      "price":"1.5",
      "datecreated":"1535734800",
      "status":"1",
      "tendangnhap":"nguyenanbtc"
   },
   {  
      "id":"457",
      "member_id":"97",
      "price":"3.5",
      "datecreated":"1535734800",
      "status":"1",
      "tendangnhap":"Dmbd01"
   },
   {  
      "id":"458",
      "member_id":"98",
      "price":"12",
      "datecreated":"1535734800",
      "status":"1",
      "tendangnhap":"sontyphu"
   },
   {  
      "id":"459",
      "member_id":"105",
      "price":"1.5",
      "datecreated":"1535734800",
      "status":"1",
      "tendangnhap":"globalteam"
   },
   {  
      "id":"460",
      "member_id":"106",
      "price":"3.5",
      "datecreated":"1535734800",
      "status":"1",
      "tendangnhap":"Dmsg"
   },
   {  
      "id":"461",
      "member_id":"108",
      "price":"3.5",
      "datecreated":"1535734800",
      "status":"1",
      "tendangnhap":"Thanhconguv"
   },
   {  
      "id":"462",
      "member_id":"109",
      "price":"50",
      "datecreated":"1535734800",
      "status":"1",
      "tendangnhap":"winwin2018"
   },
   {  
      "id":"463",
      "member_id":"110",
      "price":"1.5",
      "datecreated":"1535734800",
      "status":"1",
      "tendangnhap":"winwin01"
   },
   {  
      "id":"464",
      "member_id":"111",
      "price":"1.5",
      "datecreated":"1535734800",
      "status":"1",
      "tendangnhap":"typhuhnvn"
   },
   {  
      "id":"465",
      "member_id":"112",
      "price":"1.5",
      "datecreated":"1535734800",
      "status":"1",
      "tendangnhap":"winwin02"
   },
   {  
      "id":"466",
      "member_id":"1",
      "price":"600",
      "datecreated":"1535821200",
      "status":"1",
      "tendangnhap":"00000001"
   },
   {  
      "id":"467",
      "member_id":"70",
      "price":"50",
      "datecreated":"1535821200",
      "status":"1",
      "tendangnhap":"srilankadiamond"
   },
   {  
      "id":"468",
      "member_id":"71",
      "price":"50",
      "datecreated":"1535821200",
      "status":"1",
      "tendangnhap":"vignessri"
   },
   {  
      "id":"469",
      "member_id":"72",
      "price":"50",
      "datecreated":"1535821200",
      "status":"1",
      "tendangnhap":"kapila"
   },
   {  
      "id":"470",
      "member_id":"73",
      "price":"50",
      "datecreated":"1535821200",
      "status":"1",
      "tendangnhap":"sampath"
   },
   {  
      "id":"471",
      "member_id":"74",
      "price":"50",
      "datecreated":"1535821200",
      "status":"1",
      "tendangnhap":"global"
   },
   {  
      "id":"472",
      "member_id":"75",
      "price":"50",
      "datecreated":"1535821200",
      "status":"1",
      "tendangnhap":"global01"
   },
   {  
      "id":"473",
      "member_id":"76",
      "price":"50",
      "datecreated":"1535821200",
      "status":"1",
      "tendangnhap":"dmvn"
   },
   {  
      "id":"474",
      "member_id":"81",
      "price":"3.5",
      "datecreated":"1535821200",
      "status":"1",
      "tendangnhap":"dmvn01"
   },
   {  
      "id":"475",
      "member_id":"82",
      "price":"3.5",
      "datecreated":"1535821200",
      "status":"1",
      "tendangnhap":"dmvn02"
   },
   {  
      "id":"476",
      "member_id":"83",
      "price":"3.5",
      "datecreated":"1535821200",
      "status":"1",
      "tendangnhap":"dmvn03"
   },
   {  
      "id":"477",
      "member_id":"84",
      "price":"3.5",
      "datecreated":"1535821200",
      "status":"1",
      "tendangnhap":"chaminda"
   },
   {  
      "id":"478",
      "member_id":"85",
      "price":"3.5",
      "datecreated":"1535821200",
      "status":"1",
      "tendangnhap":"mahinda"
   },
   {  
      "id":"479",
      "member_id":"86",
      "price":"3.5",
      "datecreated":"1535821200",
      "status":"1",
      "tendangnhap":"nimal"
   },
   {  
      "id":"480",
      "member_id":"87",
      "price":"3.5",
      "datecreated":"1535821200",
      "status":"1",
      "tendangnhap":"sarath"
   },
   {  
      "id":"481",
      "member_id":"88",
      "price":"3.5",
      "datecreated":"1535821200",
      "status":"1",
      "tendangnhap":"carlo"
   },
   {  
      "id":"482",
      "member_id":"89",
      "price":"3.5",
      "datecreated":"1535821200",
      "status":"1",
      "tendangnhap":"ruwan"
   },
   {  
      "id":"483",
      "member_id":"90",
      "price":"50",
      "datecreated":"1535821200",
      "status":"1",
      "tendangnhap":"hecjes"
   },
   {  
      "id":"484",
      "member_id":"91",
      "price":"1.8",
      "datecreated":"1535821200",
      "status":"1",
      "tendangnhap":"typhu"
   },
   {  
      "id":"485",
      "member_id":"94",
      "price":"3.5",
      "datecreated":"1535821200",
      "status":"1",
      "tendangnhap":"typhu3"
   },
   {  
      "id":"486",
      "member_id":"95",
      "price":"3.5",
      "datecreated":"1535821200",
      "status":"1",
      "tendangnhap":"trieuphuusd"
   },
   {  
      "id":"487",
      "member_id":"96",
      "price":"1.5",
      "datecreated":"1535821200",
      "status":"1",
      "tendangnhap":"nguyenanbtc"
   },
   {  
      "id":"488",
      "member_id":"97",
      "price":"3.5",
      "datecreated":"1535821200",
      "status":"1",
      "tendangnhap":"Dmbd01"
   },
   {  
      "id":"489",
      "member_id":"98",
      "price":"12",
      "datecreated":"1535821200",
      "status":"1",
      "tendangnhap":"sontyphu"
   },
   {  
      "id":"490",
      "member_id":"105",
      "price":"1.5",
      "datecreated":"1535821200",
      "status":"1",
      "tendangnhap":"globalteam"
   },
   {  
      "id":"491",
      "member_id":"106",
      "price":"3.5",
      "datecreated":"1535821200",
      "status":"1",
      "tendangnhap":"Dmsg"
   },
   {  
      "id":"492",
      "member_id":"108",
      "price":"3.5",
      "datecreated":"1535821200",
      "status":"1",
      "tendangnhap":"Thanhconguv"
   },
   {  
      "id":"493",
      "member_id":"109",
      "price":"50",
      "datecreated":"1535821200",
      "status":"1",
      "tendangnhap":"winwin2018"
   },
   {  
      "id":"494",
      "member_id":"110",
      "price":"1.5",
      "datecreated":"1535821200",
      "status":"1",
      "tendangnhap":"winwin01"
   },
   {  
      "id":"495",
      "member_id":"111",
      "price":"1.5",
      "datecreated":"1535821200",
      "status":"1",
      "tendangnhap":"typhuhnvn"
   },
   {  
      "id":"496",
      "member_id":"112",
      "price":"1.5",
      "datecreated":"1535821200",
      "status":"1",
      "tendangnhap":"winwin02"
   },
   {  
      "id":"497",
      "member_id":"1",
      "price":"600",
      "datecreated":"1535907600",
      "status":"1",
      "tendangnhap":"00000001"
   },
   {  
      "id":"498",
      "member_id":"70",
      "price":"50",
      "datecreated":"1535907600",
      "status":"1",
      "tendangnhap":"srilankadiamond"
   },
   {  
      "id":"499",
      "member_id":"71",
      "price":"50",
      "datecreated":"1535907600",
      "status":"1",
      "tendangnhap":"vignessri"
   },
   {  
      "id":"500",
      "member_id":"72",
      "price":"50",
      "datecreated":"1535907600",
      "status":"1",
      "tendangnhap":"kapila"
   },
   {  
      "id":"501",
      "member_id":"73",
      "price":"50",
      "datecreated":"1535907600",
      "status":"1",
      "tendangnhap":"sampath"
   },
   {  
      "id":"502",
      "member_id":"74",
      "price":"50",
      "datecreated":"1535907600",
      "status":"1",
      "tendangnhap":"global"
   },
   {  
      "id":"503",
      "member_id":"75",
      "price":"50",
      "datecreated":"1535907600",
      "status":"1",
      "tendangnhap":"global01"
   },
   {  
      "id":"504",
      "member_id":"76",
      "price":"50",
      "datecreated":"1535907600",
      "status":"1",
      "tendangnhap":"dmvn"
   },
   {  
      "id":"505",
      "member_id":"81",
      "price":"3.5",
      "datecreated":"1535907600",
      "status":"1",
      "tendangnhap":"dmvn01"
   },
   {  
      "id":"506",
      "member_id":"82",
      "price":"3.5",
      "datecreated":"1535907600",
      "status":"1",
      "tendangnhap":"dmvn02"
   },
   {  
      "id":"507",
      "member_id":"83",
      "price":"3.5",
      "datecreated":"1535907600",
      "status":"1",
      "tendangnhap":"dmvn03"
   },
   {  
      "id":"508",
      "member_id":"84",
      "price":"3.5",
      "datecreated":"1535907600",
      "status":"1",
      "tendangnhap":"chaminda"
   },
   {  
      "id":"509",
      "member_id":"85",
      "price":"3.5",
      "datecreated":"1535907600",
      "status":"1",
      "tendangnhap":"mahinda"
   },
   {  
      "id":"510",
      "member_id":"86",
      "price":"3.5",
      "datecreated":"1535907600",
      "status":"1",
      "tendangnhap":"nimal"
   },
   {  
      "id":"511",
      "member_id":"87",
      "price":"3.5",
      "datecreated":"1535907600",
      "status":"1",
      "tendangnhap":"sarath"
   },
   {  
      "id":"512",
      "member_id":"88",
      "price":"3.5",
      "datecreated":"1535907600",
      "status":"1",
      "tendangnhap":"carlo"
   },
   {  
      "id":"513",
      "member_id":"89",
      "price":"3.5",
      "datecreated":"1535907600",
      "status":"1",
      "tendangnhap":"ruwan"
   },
   {  
      "id":"514",
      "member_id":"90",
      "price":"50",
      "datecreated":"1535907600",
      "status":"1",
      "tendangnhap":"hecjes"
   },
   {  
      "id":"515",
      "member_id":"91",
      "price":"1.8",
      "datecreated":"1535907600",
      "status":"1",
      "tendangnhap":"typhu"
   },
   {  
      "id":"516",
      "member_id":"94",
      "price":"3.5",
      "datecreated":"1535907600",
      "status":"1",
      "tendangnhap":"typhu3"
   },
   {  
      "id":"517",
      "member_id":"95",
      "price":"3.5",
      "datecreated":"1535907600",
      "status":"1",
      "tendangnhap":"trieuphuusd"
   },
   {  
      "id":"518",
      "member_id":"96",
      "price":"1.5",
      "datecreated":"1535907600",
      "status":"1",
      "tendangnhap":"nguyenanbtc"
   },
   {  
      "id":"519",
      "member_id":"97",
      "price":"3.5",
      "datecreated":"1535907600",
      "status":"1",
      "tendangnhap":"Dmbd01"
   },
   {  
      "id":"520",
      "member_id":"98",
      "price":"12",
      "datecreated":"1535907600",
      "status":"1",
      "tendangnhap":"sontyphu"
   },
   {  
      "id":"521",
      "member_id":"105",
      "price":"1.5",
      "datecreated":"1535907600",
      "status":"1",
      "tendangnhap":"globalteam"
   },
   {  
      "id":"522",
      "member_id":"106",
      "price":"3.5",
      "datecreated":"1535907600",
      "status":"1",
      "tendangnhap":"Dmsg"
   },
   {  
      "id":"523",
      "member_id":"108",
      "price":"3.5",
      "datecreated":"1535907600",
      "status":"1",
      "tendangnhap":"Thanhconguv"
   },
   {  
      "id":"524",
      "member_id":"109",
      "price":"50",
      "datecreated":"1535907600",
      "status":"1",
      "tendangnhap":"winwin2018"
   },
   {  
      "id":"525",
      "member_id":"110",
      "price":"1.5",
      "datecreated":"1535907600",
      "status":"1",
      "tendangnhap":"winwin01"
   },
   {  
      "id":"526",
      "member_id":"111",
      "price":"1.5",
      "datecreated":"1535907600",
      "status":"1",
      "tendangnhap":"typhuhnvn"
   },
   {  
      "id":"527",
      "member_id":"112",
      "price":"1.5",
      "datecreated":"1535907600",
      "status":"1",
      "tendangnhap":"winwin02"
   },
   {  
      "id":"528",
      "member_id":"1",
      "price":"600",
      "datecreated":"1535994000",
      "status":"1",
      "tendangnhap":"00000001"
   },
   {  
      "id":"529",
      "member_id":"70",
      "price":"50",
      "datecreated":"1535994000",
      "status":"1",
      "tendangnhap":"srilankadiamond"
   },
   {  
      "id":"530",
      "member_id":"71",
      "price":"50",
      "datecreated":"1535994000",
      "status":"1",
      "tendangnhap":"vignessri"
   },
   {  
      "id":"531",
      "member_id":"72",
      "price":"50",
      "datecreated":"1535994000",
      "status":"1",
      "tendangnhap":"kapila"
   },
   {  
      "id":"532",
      "member_id":"73",
      "price":"50",
      "datecreated":"1535994000",
      "status":"1",
      "tendangnhap":"sampath"
   },
   {  
      "id":"533",
      "member_id":"74",
      "price":"50",
      "datecreated":"1535994000",
      "status":"1",
      "tendangnhap":"global"
   },
   {  
      "id":"534",
      "member_id":"75",
      "price":"50",
      "datecreated":"1535994000",
      "status":"1",
      "tendangnhap":"global01"
   },
   {  
      "id":"535",
      "member_id":"76",
      "price":"50",
      "datecreated":"1535994000",
      "status":"1",
      "tendangnhap":"dmvn"
   },
   {  
      "id":"536",
      "member_id":"81",
      "price":"3.5",
      "datecreated":"1535994000",
      "status":"1",
      "tendangnhap":"dmvn01"
   },
   {  
      "id":"537",
      "member_id":"82",
      "price":"3.5",
      "datecreated":"1535994000",
      "status":"1",
      "tendangnhap":"dmvn02"
   },
   {  
      "id":"538",
      "member_id":"83",
      "price":"3.5",
      "datecreated":"1535994000",
      "status":"1",
      "tendangnhap":"dmvn03"
   },
   {  
      "id":"539",
      "member_id":"84",
      "price":"3.5",
      "datecreated":"1535994000",
      "status":"1",
      "tendangnhap":"chaminda"
   },
   {  
      "id":"540",
      "member_id":"85",
      "price":"3.5",
      "datecreated":"1535994000",
      "status":"1",
      "tendangnhap":"mahinda"
   },
   {  
      "id":"541",
      "member_id":"86",
      "price":"3.5",
      "datecreated":"1535994000",
      "status":"1",
      "tendangnhap":"nimal"
   },
   {  
      "id":"542",
      "member_id":"87",
      "price":"3.5",
      "datecreated":"1535994000",
      "status":"1",
      "tendangnhap":"sarath"
   },
   {  
      "id":"543",
      "member_id":"88",
      "price":"3.5",
      "datecreated":"1535994000",
      "status":"1",
      "tendangnhap":"carlo"
   },
   {  
      "id":"544",
      "member_id":"89",
      "price":"3.5",
      "datecreated":"1535994000",
      "status":"1",
      "tendangnhap":"ruwan"
   },
   {  
      "id":"545",
      "member_id":"90",
      "price":"50",
      "datecreated":"1535994000",
      "status":"1",
      "tendangnhap":"hecjes"
   },
   {  
      "id":"546",
      "member_id":"91",
      "price":"1.8",
      "datecreated":"1535994000",
      "status":"1",
      "tendangnhap":"typhu"
   },
   {  
      "id":"547",
      "member_id":"94",
      "price":"3.5",
      "datecreated":"1535994000",
      "status":"1",
      "tendangnhap":"typhu3"
   },
   {  
      "id":"548",
      "member_id":"95",
      "price":"3.5",
      "datecreated":"1535994000",
      "status":"1",
      "tendangnhap":"trieuphuusd"
   },
   {  
      "id":"549",
      "member_id":"96",
      "price":"1.5",
      "datecreated":"1535994000",
      "status":"1",
      "tendangnhap":"nguyenanbtc"
   },
   {  
      "id":"550",
      "member_id":"97",
      "price":"3.5",
      "datecreated":"1535994000",
      "status":"1",
      "tendangnhap":"Dmbd01"
   },
   {  
      "id":"551",
      "member_id":"98",
      "price":"12",
      "datecreated":"1535994000",
      "status":"1",
      "tendangnhap":"sontyphu"
   },
   {  
      "id":"552",
      "member_id":"105",
      "price":"1.5",
      "datecreated":"1535994000",
      "status":"1",
      "tendangnhap":"globalteam"
   },
   {  
      "id":"553",
      "member_id":"106",
      "price":"3.5",
      "datecreated":"1535994000",
      "status":"1",
      "tendangnhap":"Dmsg"
   },
   {  
      "id":"554",
      "member_id":"108",
      "price":"3.5",
      "datecreated":"1535994000",
      "status":"1",
      "tendangnhap":"Thanhconguv"
   },
   {  
      "id":"555",
      "member_id":"109",
      "price":"50",
      "datecreated":"1535994000",
      "status":"1",
      "tendangnhap":"winwin2018"
   },
   {  
      "id":"556",
      "member_id":"110",
      "price":"1.5",
      "datecreated":"1535994000",
      "status":"1",
      "tendangnhap":"winwin01"
   },
   {  
      "id":"557",
      "member_id":"111",
      "price":"1.5",
      "datecreated":"1535994000",
      "status":"1",
      "tendangnhap":"typhuhnvn"
   },
   {  
      "id":"558",
      "member_id":"112",
      "price":"1.5",
      "datecreated":"1535994000",
      "status":"1",
      "tendangnhap":"winwin02"
   },
   {  
      "id":"559",
      "member_id":"1",
      "price":"600",
      "datecreated":"1536080400",
      "status":"1",
      "tendangnhap":"00000001"
   },
   {  
      "id":"560",
      "member_id":"70",
      "price":"50",
      "datecreated":"1536080400",
      "status":"1",
      "tendangnhap":"srilankadiamond"
   },
   {  
      "id":"561",
      "member_id":"71",
      "price":"50",
      "datecreated":"1536080400",
      "status":"1",
      "tendangnhap":"vignessri"
   },
   {  
      "id":"562",
      "member_id":"72",
      "price":"50",
      "datecreated":"1536080400",
      "status":"1",
      "tendangnhap":"kapila"
   },
   {  
      "id":"563",
      "member_id":"73",
      "price":"50",
      "datecreated":"1536080400",
      "status":"1",
      "tendangnhap":"sampath"
   },
   {  
      "id":"564",
      "member_id":"74",
      "price":"50",
      "datecreated":"1536080400",
      "status":"1",
      "tendangnhap":"global"
   },
   {  
      "id":"565",
      "member_id":"75",
      "price":"50",
      "datecreated":"1536080400",
      "status":"1",
      "tendangnhap":"global01"
   },
   {  
      "id":"566",
      "member_id":"76",
      "price":"50",
      "datecreated":"1536080400",
      "status":"1",
      "tendangnhap":"dmvn"
   },
   {  
      "id":"567",
      "member_id":"81",
      "price":"3.5",
      "datecreated":"1536080400",
      "status":"1",
      "tendangnhap":"dmvn01"
   },
   {  
      "id":"568",
      "member_id":"82",
      "price":"3.5",
      "datecreated":"1536080400",
      "status":"1",
      "tendangnhap":"dmvn02"
   },
   {  
      "id":"569",
      "member_id":"83",
      "price":"3.5",
      "datecreated":"1536080400",
      "status":"1",
      "tendangnhap":"dmvn03"
   },
   {  
      "id":"570",
      "member_id":"84",
      "price":"3.5",
      "datecreated":"1536080400",
      "status":"1",
      "tendangnhap":"chaminda"
   },
   {  
      "id":"571",
      "member_id":"85",
      "price":"3.5",
      "datecreated":"1536080400",
      "status":"1",
      "tendangnhap":"mahinda"
   },
   {  
      "id":"572",
      "member_id":"86",
      "price":"3.5",
      "datecreated":"1536080400",
      "status":"1",
      "tendangnhap":"nimal"
   },
   {  
      "id":"573",
      "member_id":"87",
      "price":"3.5",
      "datecreated":"1536080400",
      "status":"1",
      "tendangnhap":"sarath"
   },
   {  
      "id":"574",
      "member_id":"88",
      "price":"3.5",
      "datecreated":"1536080400",
      "status":"1",
      "tendangnhap":"carlo"
   },
   {  
      "id":"575",
      "member_id":"89",
      "price":"3.5",
      "datecreated":"1536080400",
      "status":"1",
      "tendangnhap":"ruwan"
   },
   {  
      "id":"576",
      "member_id":"90",
      "price":"50",
      "datecreated":"1536080400",
      "status":"1",
      "tendangnhap":"hecjes"
   },
   {  
      "id":"577",
      "member_id":"91",
      "price":"1.8",
      "datecreated":"1536080400",
      "status":"1",
      "tendangnhap":"typhu"
   },
   {  
      "id":"578",
      "member_id":"94",
      "price":"3.5",
      "datecreated":"1536080400",
      "status":"1",
      "tendangnhap":"typhu3"
   },
   {  
      "id":"579",
      "member_id":"95",
      "price":"3.5",
      "datecreated":"1536080400",
      "status":"1",
      "tendangnhap":"trieuphuusd"
   },
   {  
      "id":"580",
      "member_id":"96",
      "price":"1.5",
      "datecreated":"1536080400",
      "status":"1",
      "tendangnhap":"nguyenanbtc"
   },
   {  
      "id":"581",
      "member_id":"97",
      "price":"3.5",
      "datecreated":"1536080400",
      "status":"1",
      "tendangnhap":"Dmbd01"
   },
   {  
      "id":"582",
      "member_id":"98",
      "price":"12",
      "datecreated":"1536080400",
      "status":"1",
      "tendangnhap":"sontyphu"
   },
   {  
      "id":"583",
      "member_id":"105",
      "price":"1.5",
      "datecreated":"1536080400",
      "status":"1",
      "tendangnhap":"globalteam"
   },
   {  
      "id":"584",
      "member_id":"106",
      "price":"3.5",
      "datecreated":"1536080400",
      "status":"1",
      "tendangnhap":"Dmsg"
   },
   {  
      "id":"585",
      "member_id":"108",
      "price":"3.5",
      "datecreated":"1536080400",
      "status":"1",
      "tendangnhap":"Thanhconguv"
   },
   {  
      "id":"586",
      "member_id":"109",
      "price":"50",
      "datecreated":"1536080400",
      "status":"1",
      "tendangnhap":"winwin2018"
   },
   {  
      "id":"587",
      "member_id":"110",
      "price":"1.5",
      "datecreated":"1536080400",
      "status":"1",
      "tendangnhap":"winwin01"
   },
   {  
      "id":"588",
      "member_id":"111",
      "price":"1.5",
      "datecreated":"1536080400",
      "status":"1",
      "tendangnhap":"typhuhnvn"
   },
   {  
      "id":"589",
      "member_id":"112",
      "price":"1.5",
      "datecreated":"1536080400",
      "status":"1",
      "tendangnhap":"winwin02"
   },
   {  
      "id":"590",
      "member_id":"1",
      "price":"600",
      "datecreated":"1536166800",
      "status":"1",
      "tendangnhap":"00000001"
   },
   {  
      "id":"591",
      "member_id":"70",
      "price":"50",
      "datecreated":"1536166800",
      "status":"1",
      "tendangnhap":"srilankadiamond"
   },
   {  
      "id":"592",
      "member_id":"71",
      "price":"50",
      "datecreated":"1536166800",
      "status":"1",
      "tendangnhap":"vignessri"
   },
   {  
      "id":"593",
      "member_id":"72",
      "price":"50",
      "datecreated":"1536166800",
      "status":"1",
      "tendangnhap":"kapila"
   },
   {  
      "id":"594",
      "member_id":"73",
      "price":"50",
      "datecreated":"1536166800",
      "status":"1",
      "tendangnhap":"sampath"
   },
   {  
      "id":"595",
      "member_id":"74",
      "price":"50",
      "datecreated":"1536166800",
      "status":"1",
      "tendangnhap":"global"
   },
   {  
      "id":"596",
      "member_id":"75",
      "price":"50",
      "datecreated":"1536166800",
      "status":"1",
      "tendangnhap":"global01"
   },
   {  
      "id":"597",
      "member_id":"76",
      "price":"50",
      "datecreated":"1536166800",
      "status":"1",
      "tendangnhap":"dmvn"
   },
   {  
      "id":"598",
      "member_id":"81",
      "price":"3.5",
      "datecreated":"1536166800",
      "status":"1",
      "tendangnhap":"dmvn01"
   },
   {  
      "id":"599",
      "member_id":"82",
      "price":"3.5",
      "datecreated":"1536166800",
      "status":"1",
      "tendangnhap":"dmvn02"
   },
   {  
      "id":"600",
      "member_id":"83",
      "price":"3.5",
      "datecreated":"1536166800",
      "status":"1",
      "tendangnhap":"dmvn03"
   },
   {  
      "id":"601",
      "member_id":"84",
      "price":"3.5",
      "datecreated":"1536166800",
      "status":"1",
      "tendangnhap":"chaminda"
   },
   {  
      "id":"602",
      "member_id":"85",
      "price":"3.5",
      "datecreated":"1536166800",
      "status":"1",
      "tendangnhap":"mahinda"
   },
   {  
      "id":"603",
      "member_id":"86",
      "price":"3.5",
      "datecreated":"1536166800",
      "status":"1",
      "tendangnhap":"nimal"
   },
   {  
      "id":"604",
      "member_id":"87",
      "price":"3.5",
      "datecreated":"1536166800",
      "status":"1",
      "tendangnhap":"sarath"
   },
   {  
      "id":"605",
      "member_id":"88",
      "price":"3.5",
      "datecreated":"1536166800",
      "status":"1",
      "tendangnhap":"carlo"
   },
   {  
      "id":"606",
      "member_id":"89",
      "price":"3.5",
      "datecreated":"1536166800",
      "status":"1",
      "tendangnhap":"ruwan"
   },
   {  
      "id":"607",
      "member_id":"90",
      "price":"50",
      "datecreated":"1536166800",
      "status":"1",
      "tendangnhap":"hecjes"
   },
   {  
      "id":"608",
      "member_id":"91",
      "price":"1.8",
      "datecreated":"1536166800",
      "status":"1",
      "tendangnhap":"typhu"
   },
   {  
      "id":"609",
      "member_id":"94",
      "price":"3.5",
      "datecreated":"1536166800",
      "status":"1",
      "tendangnhap":"typhu3"
   },
   {  
      "id":"610",
      "member_id":"95",
      "price":"3.5",
      "datecreated":"1536166800",
      "status":"1",
      "tendangnhap":"trieuphuusd"
   },
   {  
      "id":"611",
      "member_id":"96",
      "price":"1.5",
      "datecreated":"1536166800",
      "status":"1",
      "tendangnhap":"nguyenanbtc"
   },
   {  
      "id":"612",
      "member_id":"97",
      "price":"3.5",
      "datecreated":"1536166800",
      "status":"1",
      "tendangnhap":"Dmbd01"
   },
   {  
      "id":"613",
      "member_id":"98",
      "price":"12",
      "datecreated":"1536166800",
      "status":"1",
      "tendangnhap":"sontyphu"
   },
   {  
      "id":"614",
      "member_id":"105",
      "price":"1.5",
      "datecreated":"1536166800",
      "status":"1",
      "tendangnhap":"globalteam"
   },
   {  
      "id":"615",
      "member_id":"106",
      "price":"3.5",
      "datecreated":"1536166800",
      "status":"1",
      "tendangnhap":"Dmsg"
   },
   {  
      "id":"616",
      "member_id":"108",
      "price":"3.5",
      "datecreated":"1536166800",
      "status":"1",
      "tendangnhap":"Thanhconguv"
   },
   {  
      "id":"617",
      "member_id":"109",
      "price":"50",
      "datecreated":"1536166800",
      "status":"1",
      "tendangnhap":"winwin2018"
   },
   {  
      "id":"618",
      "member_id":"110",
      "price":"1.5",
      "datecreated":"1536166800",
      "status":"1",
      "tendangnhap":"winwin01"
   },
   {  
      "id":"619",
      "member_id":"111",
      "price":"1.5",
      "datecreated":"1536166800",
      "status":"1",
      "tendangnhap":"typhuhnvn"
   },
   {  
      "id":"620",
      "member_id":"112",
      "price":"1.5",
      "datecreated":"1536166800",
      "status":"1",
      "tendangnhap":"winwin02"
   },
   {  
      "id":"621",
      "member_id":"1",
      "price":"600",
      "datecreated":"1536253200",
      "status":"1",
      "tendangnhap":"00000001"
   },
   {  
      "id":"622",
      "member_id":"70",
      "price":"50",
      "datecreated":"1536253200",
      "status":"1",
      "tendangnhap":"srilankadiamond"
   },
   {  
      "id":"623",
      "member_id":"71",
      "price":"50",
      "datecreated":"1536253200",
      "status":"1",
      "tendangnhap":"vignessri"
   },
   {  
      "id":"624",
      "member_id":"72",
      "price":"50",
      "datecreated":"1536253200",
      "status":"1",
      "tendangnhap":"kapila"
   },
   {  
      "id":"625",
      "member_id":"73",
      "price":"50",
      "datecreated":"1536253200",
      "status":"1",
      "tendangnhap":"sampath"
   },
   {  
      "id":"626",
      "member_id":"74",
      "price":"50",
      "datecreated":"1536253200",
      "status":"1",
      "tendangnhap":"global"
   },
   {  
      "id":"627",
      "member_id":"75",
      "price":"50",
      "datecreated":"1536253200",
      "status":"1",
      "tendangnhap":"global01"
   },
   {  
      "id":"628",
      "member_id":"76",
      "price":"50",
      "datecreated":"1536253200",
      "status":"1",
      "tendangnhap":"dmvn"
   },
   {  
      "id":"629",
      "member_id":"81",
      "price":"3.5",
      "datecreated":"1536253200",
      "status":"1",
      "tendangnhap":"dmvn01"
   },
   {  
      "id":"630",
      "member_id":"82",
      "price":"3.5",
      "datecreated":"1536253200",
      "status":"1",
      "tendangnhap":"dmvn02"
   },
   {  
      "id":"631",
      "member_id":"83",
      "price":"3.5",
      "datecreated":"1536253200",
      "status":"1",
      "tendangnhap":"dmvn03"
   },
   {  
      "id":"632",
      "member_id":"84",
      "price":"3.5",
      "datecreated":"1536253200",
      "status":"1",
      "tendangnhap":"chaminda"
   },
   {  
      "id":"633",
      "member_id":"85",
      "price":"3.5",
      "datecreated":"1536253200",
      "status":"1",
      "tendangnhap":"mahinda"
   },
   {  
      "id":"634",
      "member_id":"86",
      "price":"3.5",
      "datecreated":"1536253200",
      "status":"1",
      "tendangnhap":"nimal"
   },
   {  
      "id":"635",
      "member_id":"87",
      "price":"3.5",
      "datecreated":"1536253200",
      "status":"1",
      "tendangnhap":"sarath"
   },
   {  
      "id":"636",
      "member_id":"88",
      "price":"3.5",
      "datecreated":"1536253200",
      "status":"1",
      "tendangnhap":"carlo"
   },
   {  
      "id":"637",
      "member_id":"89",
      "price":"3.5",
      "datecreated":"1536253200",
      "status":"1",
      "tendangnhap":"ruwan"
   },
   {  
      "id":"638",
      "member_id":"90",
      "price":"50",
      "datecreated":"1536253200",
      "status":"1",
      "tendangnhap":"hecjes"
   },
   {  
      "id":"639",
      "member_id":"91",
      "price":"1.8",
      "datecreated":"1536253200",
      "status":"1",
      "tendangnhap":"typhu"
   },
   {  
      "id":"640",
      "member_id":"94",
      "price":"3.5",
      "datecreated":"1536253200",
      "status":"1",
      "tendangnhap":"typhu3"
   },
   {  
      "id":"641",
      "member_id":"95",
      "price":"3.5",
      "datecreated":"1536253200",
      "status":"1",
      "tendangnhap":"trieuphuusd"
   },
   {  
      "id":"642",
      "member_id":"96",
      "price":"1.5",
      "datecreated":"1536253200",
      "status":"1",
      "tendangnhap":"nguyenanbtc"
   },
   {  
      "id":"643",
      "member_id":"97",
      "price":"3.5",
      "datecreated":"1536253200",
      "status":"1",
      "tendangnhap":"Dmbd01"
   },
   {  
      "id":"644",
      "member_id":"98",
      "price":"12",
      "datecreated":"1536253200",
      "status":"1",
      "tendangnhap":"sontyphu"
   },
   {  
      "id":"645",
      "member_id":"105",
      "price":"1.5",
      "datecreated":"1536253200",
      "status":"1",
      "tendangnhap":"globalteam"
   },
   {  
      "id":"646",
      "member_id":"106",
      "price":"3.5",
      "datecreated":"1536253200",
      "status":"1",
      "tendangnhap":"Dmsg"
   },
   {  
      "id":"647",
      "member_id":"108",
      "price":"3.5",
      "datecreated":"1536253200",
      "status":"1",
      "tendangnhap":"Thanhconguv"
   },
   {  
      "id":"648",
      "member_id":"109",
      "price":"50",
      "datecreated":"1536253200",
      "status":"1",
      "tendangnhap":"winwin2018"
   },
   {  
      "id":"649",
      "member_id":"110",
      "price":"1.5",
      "datecreated":"1536253200",
      "status":"1",
      "tendangnhap":"winwin01"
   },
   {  
      "id":"650",
      "member_id":"111",
      "price":"1.5",
      "datecreated":"1536253200",
      "status":"1",
      "tendangnhap":"typhuhnvn"
   },
   {  
      "id":"651",
      "member_id":"112",
      "price":"1.5",
      "datecreated":"1536253200",
      "status":"1",
      "tendangnhap":"winwin02"
   },
   {  
      "id":"652",
      "member_id":"1",
      "price":"600",
      "datecreated":"1536339600",
      "status":"1",
      "tendangnhap":"00000001"
   },
   {  
      "id":"653",
      "member_id":"70",
      "price":"50",
      "datecreated":"1536339600",
      "status":"1",
      "tendangnhap":"srilankadiamond"
   },
   {  
      "id":"654",
      "member_id":"71",
      "price":"50",
      "datecreated":"1536339600",
      "status":"1",
      "tendangnhap":"vignessri"
   },
   {  
      "id":"655",
      "member_id":"72",
      "price":"50",
      "datecreated":"1536339600",
      "status":"1",
      "tendangnhap":"kapila"
   },
   {  
      "id":"656",
      "member_id":"73",
      "price":"50",
      "datecreated":"1536339600",
      "status":"1",
      "tendangnhap":"sampath"
   },
   {  
      "id":"657",
      "member_id":"74",
      "price":"50",
      "datecreated":"1536339600",
      "status":"1",
      "tendangnhap":"global"
   },
   {  
      "id":"658",
      "member_id":"75",
      "price":"50",
      "datecreated":"1536339600",
      "status":"1",
      "tendangnhap":"global01"
   },
   {  
      "id":"659",
      "member_id":"76",
      "price":"50",
      "datecreated":"1536339600",
      "status":"1",
      "tendangnhap":"dmvn"
   },
   {  
      "id":"660",
      "member_id":"81",
      "price":"3.5",
      "datecreated":"1536339600",
      "status":"1",
      "tendangnhap":"dmvn01"
   },
   {  
      "id":"661",
      "member_id":"82",
      "price":"3.5",
      "datecreated":"1536339600",
      "status":"1",
      "tendangnhap":"dmvn02"
   },
   {  
      "id":"662",
      "member_id":"83",
      "price":"3.5",
      "datecreated":"1536339600",
      "status":"1",
      "tendangnhap":"dmvn03"
   },
   {  
      "id":"663",
      "member_id":"84",
      "price":"3.5",
      "datecreated":"1536339600",
      "status":"1",
      "tendangnhap":"chaminda"
   },
   {  
      "id":"664",
      "member_id":"85",
      "price":"3.5",
      "datecreated":"1536339600",
      "status":"1",
      "tendangnhap":"mahinda"
   },
   {  
      "id":"665",
      "member_id":"86",
      "price":"3.5",
      "datecreated":"1536339600",
      "status":"1",
      "tendangnhap":"nimal"
   },
   {  
      "id":"666",
      "member_id":"87",
      "price":"3.5",
      "datecreated":"1536339600",
      "status":"1",
      "tendangnhap":"sarath"
   },
   {  
      "id":"667",
      "member_id":"88",
      "price":"3.5",
      "datecreated":"1536339600",
      "status":"1",
      "tendangnhap":"carlo"
   },
   {  
      "id":"668",
      "member_id":"89",
      "price":"3.5",
      "datecreated":"1536339600",
      "status":"1",
      "tendangnhap":"ruwan"
   },
   {  
      "id":"669",
      "member_id":"90",
      "price":"50",
      "datecreated":"1536339600",
      "status":"1",
      "tendangnhap":"hecjes"
   },
   {  
      "id":"670",
      "member_id":"91",
      "price":"1.8",
      "datecreated":"1536339600",
      "status":"1",
      "tendangnhap":"typhu"
   },
   {  
      "id":"671",
      "member_id":"94",
      "price":"3.5",
      "datecreated":"1536339600",
      "status":"1",
      "tendangnhap":"typhu3"
   },
   {  
      "id":"672",
      "member_id":"95",
      "price":"3.5",
      "datecreated":"1536339600",
      "status":"1",
      "tendangnhap":"trieuphuusd"
   },
   {  
      "id":"673",
      "member_id":"96",
      "price":"1.5",
      "datecreated":"1536339600",
      "status":"1",
      "tendangnhap":"nguyenanbtc"
   },
   {  
      "id":"674",
      "member_id":"97",
      "price":"3.5",
      "datecreated":"1536339600",
      "status":"1",
      "tendangnhap":"Dmbd01"
   },
   {  
      "id":"675",
      "member_id":"98",
      "price":"12",
      "datecreated":"1536339600",
      "status":"1",
      "tendangnhap":"sontyphu"
   },
   {  
      "id":"676",
      "member_id":"105",
      "price":"1.5",
      "datecreated":"1536339600",
      "status":"1",
      "tendangnhap":"globalteam"
   },
   {  
      "id":"677",
      "member_id":"106",
      "price":"3.5",
      "datecreated":"1536339600",
      "status":"1",
      "tendangnhap":"Dmsg"
   },
   {  
      "id":"678",
      "member_id":"108",
      "price":"3.5",
      "datecreated":"1536339600",
      "status":"1",
      "tendangnhap":"Thanhconguv"
   },
   {  
      "id":"679",
      "member_id":"109",
      "price":"50",
      "datecreated":"1536339600",
      "status":"1",
      "tendangnhap":"winwin2018"
   },
   {  
      "id":"680",
      "member_id":"110",
      "price":"1.5",
      "datecreated":"1536339600",
      "status":"1",
      "tendangnhap":"winwin01"
   },
   {  
      "id":"681",
      "member_id":"111",
      "price":"1.5",
      "datecreated":"1536339600",
      "status":"1",
      "tendangnhap":"typhuhnvn"
   },
   {  
      "id":"682",
      "member_id":"112",
      "price":"1.5",
      "datecreated":"1536339600",
      "status":"1",
      "tendangnhap":"winwin02"
   },
   {  
      "id":"683",
      "member_id":"148",
      "price":"180",
      "datecreated":"1536339600",
      "status":"1",
      "tendangnhap":"dungsaigon"
   },
   {  
      "id":"684",
      "member_id":"1",
      "price":"600",
      "datecreated":"1536426000",
      "status":"1",
      "tendangnhap":"00000001"
   },
   {  
      "id":"685",
      "member_id":"70",
      "price":"50",
      "datecreated":"1536426000",
      "status":"1",
      "tendangnhap":"srilankadiamond"
   },
   {  
      "id":"686",
      "member_id":"71",
      "price":"50",
      "datecreated":"1536426000",
      "status":"1",
      "tendangnhap":"vignessri"
   },
   {  
      "id":"687",
      "member_id":"72",
      "price":"50",
      "datecreated":"1536426000",
      "status":"1",
      "tendangnhap":"kapila"
   },
   {  
      "id":"688",
      "member_id":"73",
      "price":"50",
      "datecreated":"1536426000",
      "status":"1",
      "tendangnhap":"sampath"
   },
   {  
      "id":"689",
      "member_id":"74",
      "price":"50",
      "datecreated":"1536426000",
      "status":"1",
      "tendangnhap":"global"
   },
   {  
      "id":"690",
      "member_id":"75",
      "price":"50",
      "datecreated":"1536426000",
      "status":"1",
      "tendangnhap":"global01"
   },
   {  
      "id":"691",
      "member_id":"76",
      "price":"50",
      "datecreated":"1536426000",
      "status":"1",
      "tendangnhap":"dmvn"
   },
   {  
      "id":"692",
      "member_id":"81",
      "price":"3.5",
      "datecreated":"1536426000",
      "status":"1",
      "tendangnhap":"dmvn01"
   },
   {  
      "id":"693",
      "member_id":"82",
      "price":"3.5",
      "datecreated":"1536426000",
      "status":"1",
      "tendangnhap":"dmvn02"
   },
   {  
      "id":"694",
      "member_id":"83",
      "price":"3.5",
      "datecreated":"1536426000",
      "status":"1",
      "tendangnhap":"dmvn03"
   },
   {  
      "id":"695",
      "member_id":"84",
      "price":"3.5",
      "datecreated":"1536426000",
      "status":"1",
      "tendangnhap":"chaminda"
   },
   {  
      "id":"696",
      "member_id":"85",
      "price":"3.5",
      "datecreated":"1536426000",
      "status":"1",
      "tendangnhap":"mahinda"
   },
   {  
      "id":"697",
      "member_id":"86",
      "price":"3.5",
      "datecreated":"1536426000",
      "status":"1",
      "tendangnhap":"nimal"
   },
   {  
      "id":"698",
      "member_id":"87",
      "price":"3.5",
      "datecreated":"1536426000",
      "status":"1",
      "tendangnhap":"sarath"
   },
   {  
      "id":"699",
      "member_id":"88",
      "price":"3.5",
      "datecreated":"1536426000",
      "status":"1",
      "tendangnhap":"carlo"
   },
   {  
      "id":"700",
      "member_id":"89",
      "price":"3.5",
      "datecreated":"1536426000",
      "status":"1",
      "tendangnhap":"ruwan"
   },
   {  
      "id":"701",
      "member_id":"90",
      "price":"50",
      "datecreated":"1536426000",
      "status":"1",
      "tendangnhap":"hecjes"
   },
   {  
      "id":"702",
      "member_id":"91",
      "price":"1.8",
      "datecreated":"1536426000",
      "status":"1",
      "tendangnhap":"typhu"
   },
   {  
      "id":"703",
      "member_id":"94",
      "price":"3.5",
      "datecreated":"1536426000",
      "status":"1",
      "tendangnhap":"typhu3"
   },
   {  
      "id":"704",
      "member_id":"95",
      "price":"3.5",
      "datecreated":"1536426000",
      "status":"1",
      "tendangnhap":"trieuphuusd"
   },
   {  
      "id":"705",
      "member_id":"96",
      "price":"1.5",
      "datecreated":"1536426000",
      "status":"1",
      "tendangnhap":"nguyenanbtc"
   },
   {  
      "id":"706",
      "member_id":"97",
      "price":"3.5",
      "datecreated":"1536426000",
      "status":"1",
      "tendangnhap":"Dmbd01"
   },
   {  
      "id":"707",
      "member_id":"98",
      "price":"12",
      "datecreated":"1536426000",
      "status":"1",
      "tendangnhap":"sontyphu"
   },
   {  
      "id":"708",
      "member_id":"105",
      "price":"1.5",
      "datecreated":"1536426000",
      "status":"1",
      "tendangnhap":"globalteam"
   },
   {  
      "id":"709",
      "member_id":"106",
      "price":"3.5",
      "datecreated":"1536426000",
      "status":"1",
      "tendangnhap":"Dmsg"
   },
   {  
      "id":"710",
      "member_id":"108",
      "price":"3.5",
      "datecreated":"1536426000",
      "status":"1",
      "tendangnhap":"Thanhconguv"
   },
   {  
      "id":"711",
      "member_id":"109",
      "price":"50",
      "datecreated":"1536426000",
      "status":"1",
      "tendangnhap":"winwin2018"
   },
   {  
      "id":"712",
      "member_id":"110",
      "price":"1.5",
      "datecreated":"1536426000",
      "status":"1",
      "tendangnhap":"winwin01"
   },
   {  
      "id":"713",
      "member_id":"111",
      "price":"1.5",
      "datecreated":"1536426000",
      "status":"1",
      "tendangnhap":"typhuhnvn"
   },
   {  
      "id":"714",
      "member_id":"112",
      "price":"1.5",
      "datecreated":"1536426000",
      "status":"1",
      "tendangnhap":"winwin02"
   },
   {  
      "id":"715",
      "member_id":"148",
      "price":"180",
      "datecreated":"1536426000",
      "status":"1",
      "tendangnhap":"dungsaigon"
   },
   {  
      "id":"716",
      "member_id":"1",
      "price":"600",
      "datecreated":"1536512400",
      "status":"1",
      "tendangnhap":"00000001"
   },
   {  
      "id":"717",
      "member_id":"70",
      "price":"50",
      "datecreated":"1536512400",
      "status":"1",
      "tendangnhap":"srilankadiamond"
   },
   {  
      "id":"718",
      "member_id":"71",
      "price":"50",
      "datecreated":"1536512400",
      "status":"1",
      "tendangnhap":"vignessri"
   },
   {  
      "id":"719",
      "member_id":"72",
      "price":"50",
      "datecreated":"1536512400",
      "status":"1",
      "tendangnhap":"kapila"
   },
   {  
      "id":"720",
      "member_id":"73",
      "price":"50",
      "datecreated":"1536512400",
      "status":"1",
      "tendangnhap":"sampath"
   },
   {  
      "id":"721",
      "member_id":"74",
      "price":"50",
      "datecreated":"1536512400",
      "status":"1",
      "tendangnhap":"global"
   },
   {  
      "id":"722",
      "member_id":"75",
      "price":"50",
      "datecreated":"1536512400",
      "status":"1",
      "tendangnhap":"global01"
   },
   {  
      "id":"723",
      "member_id":"76",
      "price":"50",
      "datecreated":"1536512400",
      "status":"1",
      "tendangnhap":"dmvn"
   },
   {  
      "id":"724",
      "member_id":"81",
      "price":"3.5",
      "datecreated":"1536512400",
      "status":"1",
      "tendangnhap":"dmvn01"
   },
   {  
      "id":"725",
      "member_id":"82",
      "price":"3.5",
      "datecreated":"1536512400",
      "status":"1",
      "tendangnhap":"dmvn02"
   },
   {  
      "id":"726",
      "member_id":"83",
      "price":"3.5",
      "datecreated":"1536512400",
      "status":"1",
      "tendangnhap":"dmvn03"
   },
   {  
      "id":"727",
      "member_id":"84",
      "price":"3.5",
      "datecreated":"1536512400",
      "status":"1",
      "tendangnhap":"chaminda"
   },
   {  
      "id":"728",
      "member_id":"85",
      "price":"3.5",
      "datecreated":"1536512400",
      "status":"1",
      "tendangnhap":"mahinda"
   },
   {  
      "id":"729",
      "member_id":"86",
      "price":"3.5",
      "datecreated":"1536512400",
      "status":"1",
      "tendangnhap":"nimal"
   },
   {  
      "id":"730",
      "member_id":"87",
      "price":"3.5",
      "datecreated":"1536512400",
      "status":"1",
      "tendangnhap":"sarath"
   },
   {  
      "id":"731",
      "member_id":"88",
      "price":"3.5",
      "datecreated":"1536512400",
      "status":"1",
      "tendangnhap":"carlo"
   },
   {  
      "id":"732",
      "member_id":"89",
      "price":"3.5",
      "datecreated":"1536512400",
      "status":"1",
      "tendangnhap":"ruwan"
   },
   {  
      "id":"733",
      "member_id":"90",
      "price":"50",
      "datecreated":"1536512400",
      "status":"1",
      "tendangnhap":"hecjes"
   },
   {  
      "id":"734",
      "member_id":"91",
      "price":"1.8",
      "datecreated":"1536512400",
      "status":"1",
      "tendangnhap":"typhu"
   },
   {  
      "id":"735",
      "member_id":"94",
      "price":"3.5",
      "datecreated":"1536512400",
      "status":"1",
      "tendangnhap":"typhu3"
   },
   {  
      "id":"736",
      "member_id":"95",
      "price":"3.5",
      "datecreated":"1536512400",
      "status":"1",
      "tendangnhap":"trieuphuusd"
   },
   {  
      "id":"737",
      "member_id":"96",
      "price":"1.5",
      "datecreated":"1536512400",
      "status":"1",
      "tendangnhap":"nguyenanbtc"
   },
   {  
      "id":"738",
      "member_id":"97",
      "price":"3.5",
      "datecreated":"1536512400",
      "status":"1",
      "tendangnhap":"Dmbd01"
   },
   {  
      "id":"739",
      "member_id":"98",
      "price":"12",
      "datecreated":"1536512400",
      "status":"1",
      "tendangnhap":"sontyphu"
   },
   {  
      "id":"740",
      "member_id":"105",
      "price":"1.5",
      "datecreated":"1536512400",
      "status":"1",
      "tendangnhap":"globalteam"
   },
   {  
      "id":"741",
      "member_id":"106",
      "price":"3.5",
      "datecreated":"1536512400",
      "status":"1",
      "tendangnhap":"Dmsg"
   },
   {  
      "id":"742",
      "member_id":"108",
      "price":"3.5",
      "datecreated":"1536512400",
      "status":"1",
      "tendangnhap":"Thanhconguv"
   },
   {  
      "id":"743",
      "member_id":"109",
      "price":"50",
      "datecreated":"1536512400",
      "status":"1",
      "tendangnhap":"winwin2018"
   },
   {  
      "id":"744",
      "member_id":"110",
      "price":"1.5",
      "datecreated":"1536512400",
      "status":"1",
      "tendangnhap":"winwin01"
   },
   {  
      "id":"745",
      "member_id":"111",
      "price":"1.5",
      "datecreated":"1536512400",
      "status":"1",
      "tendangnhap":"typhuhnvn"
   },
   {  
      "id":"746",
      "member_id":"112",
      "price":"1.5",
      "datecreated":"1536512400",
      "status":"1",
      "tendangnhap":"winwin02"
   },
   {  
      "id":"747",
      "member_id":"148",
      "price":"180",
      "datecreated":"1536512400",
      "status":"1",
      "tendangnhap":"dungsaigon"
   }
]